pelican/plugins/pelimoji/__init__.py
pelican/plugins/pelimoji/css.j2
pelican/plugins/pelimoji/pelimoji.py
pelimoji-1.2.0.dist-info/METADATA
pelimoji-1.2.0.dist-info/WHEEL
pelimoji-1.2.0.dist-info/entry_points.txt
pelimoji-1.2.0.dist-info/RECORD
