Metadata-Version: 2.1
Name: pelimoji
Version: 1.2.0
Summary: Pelican plugin to add custom emoji to your site
Keywords: pelican,plugin,emoji
Author-Email: Kay Ohtie <kay@coyotesin.space>
License: AGPL-3.0
Classifier: Development Status :: 5 - Production/Stable
Classifier: Environment :: Console
Classifier: Framework :: Pelican
Classifier: Framework :: Pelican :: Plugins
Classifier: Intended Audience :: End Users/Desktop
Classifier: License :: OSI Approved :: GNU Affero General Public License v3
Classifier: Operating System :: OS Independent
Classifier: Programming Language :: Python :: 3
Classifier: Programming Language :: Python :: 3.9
Classifier: Programming Language :: Python :: 3.10
Classifier: Programming Language :: Python :: 3.11
Classifier: Programming Language :: Python :: 3.12
Classifier: Programming Language :: Python :: 3.13
Classifier: Topic :: Internet :: WWW/HTTP
Classifier: Topic :: Software Development :: Libraries :: Python Modules
Project-URL: Homepage, https://github.com/pelican-plugins/pelimoji
Project-URL: Issue Tracker, https://github.com/pelican-plugins/pelimoji/issues
Project-URL: Changelog, https://github.com/pelican-plugins/pelimoji/blob/main/CHANGELOG.md
Project-URL: Funding, https://donate.getpelican.com/
Requires-Python: ~=3.9
Requires-Dist: pelican>=4.5
Requires-Dist: Pillow>=9.5
Provides-Extra: markdown
Requires-Dist: markdown>=3.4; extra == "markdown"
